README.md
setup.py
goss/__init__.py
goss/__version__.py
goss/github.py
goss.egg-info/PKG-INFO
goss.egg-info/SOURCES.txt
goss.egg-info/dependency_links.txt
goss.egg-info/entry_points.txt
goss.egg-info/requires.txt
goss.egg-info/top_level.txt
goss/app/__init__.py
goss/app/config.py
goss/app/logger.py
goss/app/release.py
goss/app/run.py
goss/app/test_utils.py
goss/app/upload_file.py
goss/app/utils.py